json_schema_himarc/__init__.py
json_schema_himarc/validation.py
json_schema_himarc/schema/himarc-register.schema.json
json_schema_himarc/schema/himarc-work.schema.json
tests/__init__.py
tests/conftest.py
tests/test_validation.py
json_schema_himarc-2.9.28.dist-info/LICENSE
json_schema_himarc-2.9.28.dist-info/METADATA
json_schema_himarc-2.9.28.dist-info/WHEEL
json_schema_himarc-2.9.28.dist-info/top_level.txt
json_schema_himarc-2.9.28.dist-info/RECORD
