Metadata-Version: 2.1
Name: json-schema-himarc
Version: 2.9.28
Summary: "Python validator for himarc JSON Schema"
Home-page: UNKNOWN
Author: "TROUVERIE Joachim"
Author-email: "jtrouverie@anybox.fr"
License: "MIT"
Keywords: "json-schema"
Platform: UNKNOWN
Classifier: License :: OSI Approved :: MIT License
Classifier: Topic :: Software Development :: Libraries
Classifier: Programming Language :: Python :: 3
Classifier: Programming Language :: Python :: 3.5
License-File: LICENSE
Requires-Dist: jsonschema==3.2.0
